{"errno":0,"errmsg":"success","baesInfo":{"word_name":"configuration","is_CRI":1,"exchange":{"word_pl":["configurations"],"word_past":[],"word_done":[],"word_ing":[],"word_third":[],"word_er":[],"word_est":[],"word_prep":[],"word_adv":[],"word_verb":[],"word_noun":[],"word_adj":[],"word_conn":[]},"symbols":[{"ph_en":"kənˌfɪgəˈreɪʃn","ph_am":"kənˌfɪgjəˈreɪʃn","ph_other":"","ph_en_mp3":"http://res.iciba.com/resource/amp3/oxford/0/b1/ba/b1ba53090e8047b9d7fdcdc76c5ca99c.mp3","ph_am_mp3":"http://res.iciba.com/resource/amp3/1/0/cc/d1/ccd1066343c95877b75b79d47c36bebe.mp3","ph_tts_mp3":"http://res-tts.iciba.com/c/c/d/ccd1066343c95877b75b79d47c36bebe.mp3","parts":[{"part":"n.","means":["布局，构造","配置","[化]（分子中原子的）组态，排列","[物]位形，组态"]}]}],"frequence":1,"word_tag":[3,4,5],"translate_type":1},"trade_means":[{"word_trade":"体育","word_mean":["阵式","阵容"]},{"word_trade":"力学","word_mean":["构型"]},{"word_trade":"化学","word_mean":["构型"]},{"word_trade":"医学","word_mean":["构型：化学上指分子中原子的空间排列，此特征可使化合物与其立体异构体相区别。参见constitution"]},{"word_trade":"数学","word_mean":["构形"]},{"word_trade":"物理学","word_mean":["位形","组态"]},{"word_trade":"生物化学","word_mean":["构型"]},{"word_trade":"自动化","word_mean":["组态"]}],"sentence":[{"Network_id":"2313323","Network_en":"Prices range from $119 to $199, depending on the particular configuration.","Network_cn":"价格因具体配置而异，从119美元至199美元不等。","tts_mp3":"http://res-tts.iciba.com/tts_new_dj//c/0/2/c022a204035168be669bca56e8be9afb.mp3","tts_size":"34K","source_type":0,"source_id":0,"source_title":"普通双语例句"},{"Network_id":"1740781","Network_en":"Geographers study the configuration of the mountains.","Network_cn":"地理学家研究山脉的地形轮廓.","tts_mp3":"http://res-tts.iciba.com/tts_new_dj//3/f/e/3fe3b48404fe3eefc43f2afd907055b5.mp3","tts_size":"15K","source_type":0,"source_id":0,"source_title":"普通双语例句"},{"Network_id":"2096936","Network_en":"The basic configuration and development trend of the cross - straits relations remain unchanged.","Network_cn":"两岸关系的基本格局和发展趋势没有改变.","tts_mp3":"http://res-tts.iciba.com/tts_new_dj//6/9/d/69d0108144c6e2143ab8714e31a125b1.mp3","tts_size":"27K","source_type":0,"source_id":0,"source_title":"普通双语例句"}],"netmean":{"PerfectNetExp":[{"id":"16408","key":"configuration","exp":"配置","url":"http://word.langfly.com/a/20120319/211427.shtml","bas":13624,"abs":"电脑常用英语单词 ... object 对象 configuration 配置 command 命令."},{"id":"45498","key":"configuration","exp":"组态","url":"http://www.pclw.com/mianfeilunwen/239.html","bas":4436,"abs":"在组态（Configuration）方面，ASP.NET采用容易阅读的XML组态文件，称为Web.Config，只要将此文件放在Web应用程序的相关目 …"},{"id":"108789","key":"configuration","exp":"构型","url":"http://dc.gdut.edu.cn/polymer/Article/ShowArticle.asp?ArticleID=22&amp;Page=2","bas":1546,"abs":"构型(Configuration)：是由原子（或取代基）在手性中心或双键上的空间排布顺序不同而产物的立体异构。)构象(Conformation)：构象 …"},{"id":"126955","key":"configuration","exp":"结构","url":"http://www.douban.com/group/topic/4824898/","bas":1270,"abs":"英语词根词缀记忆大全 ... transfigure v 使变形；使改观 configuration n 结构；形状；配置 figure 形象+."}],"RelatedPhrase":[{"word":"configurability","list":[{"id":"825825","key":"configurability","exp":"可配置性","url":"http://blog.sina.com.cn/s/blog_6c76650b0100m1yh.html","bas":105,"abs":"2.产品化和可配置性(Configurability)。产品化的过程就是配置化的过程。"}]},{"word":"configurator","list":[{"id":"747470","key":"configurator","exp":"配置程序","url":"http://blog.donews.com/Nicolaszhou/archive/category/uncategorized","bas":120,"abs":"未分类 - - Nicolas’ Blog - Upholstery ... configuration 配置 configurator 配置程序 configure 配置."}]},{"word":"configurable","list":[{"id":"503636","key":"configurable","exp":"可配置","url":"http://www.eettaiwan.com/ART_8800413189_480102_NT_b64fdb38.HTM","bas":202,"abs":"而近年来可配置(Configurable)核心技术的浮现，他认为这是嵌入式控制技术持续演进的一部分，「可配置核心绝对不是另外一个单独 …"}]},{"word":"configure","list":[{"id":"331823","key":"configure","exp":"设置","url":"http://mirageqq.blog.163.com/blog/static/1967370772011101835457745/","bas":356,"abs":"3d max 中英文对照 - 小M的日志 - 网易博客 ... Cone Object 锥体 Configure 设置；配置 Configure Driver 设置驱动."},{"id":"372921","key":"configure","exp":"进入全局配置模式","url":"http://blog.club.sohu.com/wenji_list_diary_detail.php?artid=15298&amp;db=blog001P4&amp;kindid=1106","bas":304,"abs":"搜狐社区-论坛-聊天室-博客-BBS ... Clock 管理系统的时钟 Configure 进入全局配置模式 Delete 删除一个文件."}]}]},"derivation":[{"yuyuan_name":"mid 16th cent. (denoting the relative position of celestial objects): from late Latin configuratio(n-), from Latin configurare 'shape after a pattern' (see configure)"}],"collins":[{"entry":[{"posp":"N-COUNT","tran":"安排;格局;布局","def":"A configuration is an arrangement of a group of things.","example":[{"ex":"...Stonehenge, in south-western England, an ancient configuration of giant stones.","tran":"英格兰西南部的巨石阵——一座古老的巨石阵列","tts_mp3":"http://res-tts.iciba.com/tts_dj/c/d/1/cd19d60f88954e19f1d760d0477c6557.mp3","tts_size":"28K"}]},{"posp":"N-UNCOUNT","tran":"配置","def":"The configuration of a computer system is way in which all its parts, such as the hardware and software, are connected together in order for the computer to work.","example":[{"ex":"Prices range from $119 to $199, depending on the particular configuration.","tran":"价格因具体配置而异，从119美元至199美元不等。","tts_mp3":"http://res-tts.iciba.com/tts_dj/c/0/2/c022a204035168be669bca56e8be9afb.mp3","tts_size":"34K"}]}]}],"ee_mean":[{"part_name":"Noun","means":[{"word_mean":"1. an arrangement of parts or elements;","sentences":[{"sentence":"\"the outcome depends on the configuration of influences at the time\""}]},{"word_mean":"2. any spatial attributes (especially as defined by outline);","sentences":[{"sentence":"\"he could barely make out their shapes through the smoke\""}]}]}],"auth_sentence":[{"id":"41419","content":"The article mentioned configuration space with many dimensions.","link":"http://www.scientificamerican.com/article.cfm?id=was-einstein-wrong-about-relativity","short_link":"http://www.scientificamerican.com/zmmsh","source":"SA","score":"0.975","cache_status":"1","tts_mp3":"http://res-tts.iciba.com/tts_authority/e/e/5/ee5361f5bb4fe48963afd04d86033724.mp3","tts_size":"19.0","diff":"2","oral":"0","res_content":"The article mentioned <b>configuration</b> space with many dimensions.","res_content_con":"The article mentioned configuration space with many dimensions.","res_key":"ee5361f5bb4fe48963afd04d86033724","source_type":0,"source_id":0,"source_title":"普通权威例句"},{"id":"410674","content":"Not all animals have this same middle ear bone configuration.","link":"http://www.scientificamerican.com/article.cfm?id=experts-how-do-the-hammer-anvil-a&print=true","short_link":"http://www.scientificamerican.com/5p58s","source":"SA","score":"0.975","cache_status":"1","tts_mp3":"http://res-tts.iciba.com/tts_authority/2/8/5/285299fb07f267afb3fff9cf1cbce3de.mp3","tts_size":"18.0","diff":"2","oral":"0","res_content":"Not all animals have this same middle ear bone <b>configuration</b>.","res_content_con":"Not all animals have this same middle ear bone configuration.","res_key":"285299fb07f267afb3fff9cf1cbce3de","source_type":0,"source_id":0,"source_title":"普通权威例句"},{"id":"426439","content":"This is the archetype of configuration for the origin of mass.","link":"http://www.scientificamerican.com/article.cfm?id=blitz-how-dark-matter-messes-with-our-galaxy","short_link":"http://www.scientificamerican.com/vgn64","source":"SA","score":"0.9","cache_status":"1","tts_mp3":"http://res-tts.iciba.com/tts_authority/d/8/1/d819f9d1e1e68393223173a0202d83ab.mp3","tts_size":"19.0","diff":"3","oral":"0","res_content":"This is the archetype of <b>configuration</b> for the origin of mass.","res_content_con":"This is the archetype of configuration for the origin of mass.","res_key":"d819f9d1e1e68393223173a0202d83ab","source_type":0,"source_id":0,"source_title":"普通权威例句"}],"stems_affixes":[{"type":"词根","type_value":"fig","type_exp":"=do,make 表示\"做,制作\"","word_parts":[{"word_part":"n.","stems_affixes":[{"value_en":"configuration","value_cn":"轮廓,结构,配置","word_buile":"con共同+figure轮廓+ation表名词→所有的轮廓放在一起→总的结构"},{"value_en":"figment","value_cn":"虚构的东西","word_buile":"fig做,制作+ment物→做出来的东西"},{"value_en":"figure","value_cn":"体形;轮廓;数字;图形 ","word_buile":"fig做,制作+ure表名词→做出的状态,形状"}]},{"word_part":"v.","stems_affixes":[{"value_en":"figure","value_cn":"描绘;计算;推测","word_buile":"fig做,制作+ure表名词→做出的状态,形状"},{"value_en":"transfigure","value_cn":"改观;变形","word_buile":"trans改变+figure形状→改变形状"}]}]}],"bidec":{"word_name":"configuration","parts":[{"part_name":"n.","word_id":"16614","part_id":"22317","means":[{"word_mean":"构造, 形状, 外貌, 轮廓","part_id":"22317","mean_id":"40402","sentences":[{"en":"Geographers study the configuration of the mountains.","cn":"地理学家研究山脉的地形轮廓。"}]}]}]},"jushi":[{"english":"Scientists know little about the configuration of the moon's surface.","chinese":"科学家对月球表面的形状知道得很少。","mp3":"http://res-tts.iciba.com/tts_synusage/2/4/d/24dbbf3bdbb76bf861ac921d39b0fb58.mp3"},{"english":"Geographers study the configuration of the mountains.","chinese":"地理学家研究山脉的地形轮廓。","mp3":"http://res-tts.iciba.com/tts_synusage/3/f/e/3fe3b48404fe3eefc43f2afd907055b5.mp3"}],"traditional":"","_word_flag":1,"exchanges":["configurations","configuration"]}