{"errno":0,"errmsg":"success","baesInfo":{"word_name":"magical","is_CRI":"1","exchange":{"word_pl":[],"word_third":[],"word_past":[],"word_done":[],"word_ing":[],"word_er":[],"word_est":[],"word_prep":[],"word_adv":["magically"],"word_verb":[],"word_noun":[],"word_adj":[],"word_conn":[]},"symbols":[{"ph_en":"ˈmædʒɪkl","ph_am":"ˈmædʒɪkəl","ph_other":"","ph_en_mp3":"http://res.iciba.com/resource/amp3/oxford/0/f6/a0/f6a0f72bc7bfb354c63586ddc79143aa.mp3","ph_am_mp3":"http://res.iciba.com/resource/amp3/1/0/f1/30/f130c2f895abe730c2264892911213db.mp3","ph_tts_mp3":"http://res-tts.iciba.com/f/1/3/f130c2f895abe730c2264892911213db.mp3","parts":[{"part":"adj.","means":["魔力的，不可思议的，迷人的","神","幻","神奇"]}]}],"frequence":2,"word_tag":[4],"translate_type":1},"sentence":[{"Network_id":"2340856","Network_en":"The beautiful island of Cyprus is a magical place to get married.","Network_cn":"美丽的塞浦路斯岛是缔结良缘的美妙之地。","tts_mp3":"http://res-tts.iciba.com/tts_new_dj//7/4/c/74cdd7d60a1980dc6bed3bc328df72e5.mp3","tts_size":"19K","source_type":0,"source_id":0,"source_title":"普通双语例句"},{"Network_id":"2363238","Network_en":"The story is a magical mix of fantasy and reality.","Network_cn":"这个故事是幻想与现实的奇妙结合。","tts_mp3":"http://res-tts.iciba.com/tts_new_dj//9/b/6/9b6191e291ee383164cb3708a3890715.mp3","tts_size":"16K","source_type":0,"source_id":0,"source_title":"普通双语例句"},{"Network_id":"2258137","Network_en":"Her words had a magical effect on us.","Network_cn":"她的话对我们有一种魔力般的作用。","tts_mp3":"http://res-tts.iciba.com/tts_new_dj//8/5/b/85b9a043ce5fe3f80675ecfdb6969d70.mp3","tts_size":"12K","source_type":0,"source_id":0,"source_title":"普通双语例句"}],"netmean":{"PerfectNetExp":[{"id":"296150","key":"magical","exp":"魔法的","url":"http://zhidao.baidu.com/question/82586047.html","bas":415,"abs":"跪求1000个最简单常用的英语单词_百度知道 ... 摩托车 motorbike 魔法的 magical 魔鬼 thriller."},{"id":"484341","key":"magical","exp":"魔术的","url":"http://baike.baidu.com/search/word?word=%E9%AD%94%E6%9C%AF%E7%9A%84","bas":213,"abs":"高中英语必修2_百度百科 ... Greece 希腊 magical adj 巫术的;魔术的;有魔力的 homeland n. 祖国;本国."},{"id":"674229","key":"magical","exp":"神奇的","url":"http://www.chinadaily.com.cn/language_tips/bbc/mediaenglish/2009-05/08/content_7756578.htm","bas":137,"abs":"Hot Air Balloon Accident 热气球事故-英语点津 ... bank 河岸 magical 神奇的 released 出院."},{"id":"1113239","key":"magical","exp":"魔幻","url":"http://www.uwants.com/viewthread.php?tid=9474920","bas":72,"abs":"...」,这正是自我被去主体化,真假难分,陷入笛卡儿式的魔幻(magical)角色的批评!"}],"RelatedPhrase":[{"word":"magic house","list":[{"id":"77255","key":"magic house","exp":"魔术屋","url":"http://www.suzhou.gov.cn/zgszeng/calture8life/life8in8suzhou/shopping/shopping8centers8streets/201110/t20111031_76413.shtml","bas":2358,"abs":"Suzhou China ... 天线宝宝 |Teletubbies 魔术屋 |Magic House 可可鸭 |QQ Duck."}]},{"word":"magic castle","list":[{"id":"66473","key":"magic castle","exp":"魔法城堡","url":"http://travel.enorth.com.cn/system/2012/11/01/010218180.shtml","bas":2834,"abs":"　　黑梳山的魔法城堡(Magic Castle)以及惠斯勒的树堡(Tree Fort)在本滑雪季翻修一新，比以前更具乐趣，为滑雪、乘骑以及探索山上游 …"}]},{"word":"magic power","list":[{"id":"47374","key":"magic power","exp":"魔幻力量","url":"http://www.mogo.com.cn/","bas":4222,"abs":"Mogo -- 首页 ... 《AV 大久保乐队》专访《大时代》 《Magic Power 魔幻力量》专访 《MC BigDog 大狗》专访."}]},{"word":"Egyptian magic","list":[{"id":"20083","key":"Egyptian magic","exp":"埃及魔法膏","url":"http://hh-j.taobao.com/","bas":10894,"abs":"首页-春田花花家家一生，都要漂亮下去-淘宝网 ... sleek 彩妆 Egyptian Magic 埃及魔法膏 SONOKO 庄能子."}]}]},"collins":[{"entry":[{"posp":"ADJ","tran":"施魔法的;产生魔力的","def":"Something that is magical seems to use magic or to be able to produce magic.","example":[{"ex":"...the story of Sin-Sin, a little boy who has magical powers.","tran":"一个有魔力的小男孩辛辛的故事","tts_mp3":"http://res-tts.iciba.com/tts_dj/e/b/0/eb0ee9cb074d886ac38daca11f2f311b.mp3","tts_size":"19K"}]},{"posp":"ADJ-GRADED","tran":"（地方或物体）奇妙的，神奇的","def":"You can say that a place or object is magical when it has a special mysterious quality that makes it seem wonderful and exciting.","example":[{"ex":"The beautiful island of Cyprus is a magical place to get married.","tran":"美丽的塞浦路斯岛是缔结良缘的美妙之地。","tts_mp3":"http://res-tts.iciba.com/tts_dj/7/4/c/74cdd7d60a1980dc6bed3bc328df72e5.mp3","tts_size":"19K"}]}]}],"ee_mean":[{"part_name":"Adjective","means":[{"word_mean":"1. possessing or using or characteristic of or appropriate to supernatural powers;","sentences":[{"sentence":"\"charming incantations\""},{"sentence":"\"magic signs that protect against adverse influence\""},{"sentence":"\"a magical spell\""},{"sentence":"\"'tis now the very witching time of night\"- Shakespeare"},{"sentence":"\"wizard wands\""},{"sentence":"\"wizardly powers\""}]}]}],"auth_sentence":[{"id":"7509","content":"This set makes it seem magical all over again.","link":"http://www.bbc.co.uk/music/reviews/crf9","short_link":"http://www.bbc.co.uk/4z8pg","source":"BBC","score":"1","cache_status":"1","tts_mp3":"http://res-tts.iciba.com/tts_authority/9/d/4/9d4d11f288bd579cd79b1c231e710e66.mp3","tts_size":"15.0","diff":"1","oral":"0","res_content":"This set makes it seem <b>magical</b> all over again.","res_content_con":"This set makes it seem magical all over again.","res_key":"9d4d11f288bd579cd79b1c231e710e66","source_type":0,"source_id":0,"source_title":"普通权威例句"},{"id":"32108","content":"Don't be stupid and believe in magical nonsense.","link":"http://www.scientificamerican.com/article.cfm?id=50-years-ago-scope-trial-witness&media=mobile","short_link":"http://www.scientificamerican.com/896t3","source":"SA","score":"1","cache_status":"1","tts_mp3":"http://res-tts.iciba.com/tts_authority/3/9/8/3980a11b5837cc23c7052414e3be2b07.mp3","tts_size":"15.0","diff":"2","oral":"0","res_content":"Don't be stupid and believe in <b>magical</b> nonsense.","res_content_con":"Don't be stupid and believe in magical nonsense.","res_key":"3980a11b5837cc23c7052414e3be2b07","source_type":0,"source_id":0,"source_title":"普通权威例句"},{"id":"40502","content":"Where did he get his magical powers of creation?","link":"http://www.scientificamerican.com/article.cfm?id=15-answers-to-creationist","short_link":"http://www.scientificamerican.com/gnprm","source":"SA","score":"1","cache_status":"1","tts_mp3":"http://res-tts.iciba.com/tts_authority/b/c/3/bc391578570b5f801756d435857234d4.mp3","tts_size":"15.0","diff":"1","oral":"0","res_content":"Where did he get his <b>magical</b> powers of creation?","res_content_con":"Where did he get his magical powers of creation?","res_key":"bc391578570b5f801756d435857234d4","source_type":0,"source_id":0,"source_title":"普通权威例句"}],"cetSix":{"word":"magical","count":1,"kd":[],"Sentence":[{"sentence":"Over the next two years they made their most groundbreaking work, turning the recording studio into a magical instrument of its own.","come":"出自-2013年12月阅读原文"}]},"bidec":{"word_name":"magical","parts":[{"part_name":"adj.","word_id":"6788","part_id":"8977","means":[{"word_mean":"魔力的, 不可思议的, 迷人的","part_id":"8977","mean_id":"14304","sentences":[{"en":"I used to believe my mother had magical powers.","cn":"我以前一直相信我母亲有奇妙的魔力。"}]}]}]},"traditional":"","_word_flag":1,"exchanges":["magically","magical"]}