{"errno":0,"errmsg":"success","baesInfo":{"word_name":"Danaus","is_CRI":"0","exchange":{"word_pl":[],"word_third":[],"word_past":[],"word_done":[],"word_ing":[],"word_er":[],"word_est":[],"word_prep":[],"word_adv":[],"word_verb":[],"word_noun":[],"word_adj":[],"word_conn":[]},"symbols":[{"ph_en":"ˈdæni:əs","ph_am":"ˈdæniəs","ph_other":"","ph_en_mp3":"","ph_am_mp3":"","ph_tts_mp3":"http://res-tts.iciba.com/e/c/5/ec536d6aa8d93508e0d38c0934ee05bd.mp3","parts":[{"part":"n.","means":["<希神>丹尼亚斯"]}]}],"translate_type":1},"netmean":{"PerfectNetExp":[{"id":"803695","key":"danaus","exp":"达那俄斯","url":"http://mengyue188.blog.163.com/blog/static/43850136201111217468848/","bas":109,"abs":"阿尔戈斯（Argos）的国王达那俄斯（Danaus）有50个女儿，人称达那伊得斯姐妹，即Danaides.为了和他的孪生兄弟埃古普托斯（Ae…"},{"id":"1156861","key":"danaus","exp":"斑蝶属","url":"http://baike.baidu.com/search/word?word=%E6%96%91%E8%9D%B6%E5%B1%9E","bas":69,"abs":"斑蝶属（danaus）（Danaus）命名人及年代： Linnaeus，1758年英文名： Monarch butterfly 掠食者寄生虫黑脉金斑蝶，又名大桦斑蝶、帝王 …"},{"id":"1206048","key":"danaus","exp":"丹尼亚斯","url":"http://baike.baidu.com/search/word?word=%E4%B8%B9%E5%B0%BC%E4%BA%9A%E6%96%AF","bas":66,"abs":"阿密摩涅（Amymone），丹尼亚斯（danaus）（Danaus）和欧罗巴的女儿，是尼普顿的另一位情人。当时他们的土地正遭受严重的干旱，丹尼 …"}],"RelatedPhrase":[{"word":"mengelilingi danau","list":[{"id":"15083194","key":"mengelilingi danau","exp":"游湖","url":"http://www.yoyobali.com/gotobali/phpBB2/viewtopic.php?t=6702","bas":1,"abs":"sewa kapal 租船mengelilingi danau 游湖arung jeram 泛舟"}]},{"word":"danau mala","list":[{"id":"3586964","key":"danau mala","exp":"马拉湖","url":"http://webproxy.teleprocorp.com.mx:8002/Display?what=license_install_page.mhtml","bas":12,"abs":"danant 达南danau mala 马拉湖dandobi 丹多比"}]}]},"ee_mean":[{"part_name":"Noun","means":[{"word_mean":"1. type genus of the Danaidae: monarch butterflies","sentences":[]}]}],"traditional":"","_word_flag":1,"exchanges":["danaus"]}