{"errno":0,"errmsg":"success","baesInfo":{"word_name":"peduncle","is_CRI":"0","exchange":{"word_pl":[],"word_third":[],"word_past":[],"word_done":[],"word_ing":[],"word_er":[],"word_est":[],"word_prep":[],"word_adv":[],"word_verb":[],"word_noun":[],"word_adj":[],"word_conn":[]},"symbols":[{"ph_en":"pɪ'dʌŋkl","ph_am":"pɪ'dʌŋkəl","ph_other":"","ph_en_mp3":"http://res.iciba.com/resource/amp3/0/0/1c/4f/1c4fa3c4ff9a890b943122676f5c43c5.mp3","ph_am_mp3":"http://res.iciba.com/resource/amp3/1/0/1c/4f/1c4fa3c4ff9a890b943122676f5c43c5.mp3","ph_tts_mp3":"http://res-tts.iciba.com/1/c/4/1c4fa3c4ff9a890b943122676f5c43c5.mp3","parts":[{"part":"n.","means":["花梗，梗，（肿瘤或息肉的）肉茎","腹柄"]}]}],"translate_type":1},"trade_means":[{"word_trade":"动物学","word_mean":["小柄"]},{"word_trade":"医学","word_mean":["蒂，脚，茎：茎样连接部"]},{"word_trade":"昆虫学","word_mean":["蕈状体柄","柄突","蕈狀柄","柄節"]},{"word_trade":"植物学","word_mean":["花序梗"]}],"sentence":[{"Network_id":"379643","Network_en":"Single dark blue - violet, one or more per peduncle, very floriferous.","Network_cn":"单瓣深蓝至紫罗兰色花, 每个节有一甚至更多的花梗, 很会开花.","tts_mp3":"http://res-tts.iciba.com/tts_new_dj//a/e/7/ae75eb0190a0b7abec63821e17f7277c.mp3","tts_size":"24K","source_type":0,"source_id":0,"source_title":"普通双语例句"},{"Network_id":"486585","Network_en":"Single medium lavender - blue, 3 - 7 per peduncle, hides under leaves, short - lived.","Network_cn":"单瓣花,中薰衣草色到蓝色, 每个花梗有3-7朵花,容易藏在叶子里, 花期短.","tts_mp3":"http://res-tts.iciba.com/tts_new_dj//e/e/5/ee5aedc8f33ae7b07815a1501d6cbf6c.mp3","tts_size":"31K","source_type":0,"source_id":0,"source_title":"普通双语例句"},{"Network_id":"748403","Network_en":"Each nut grows inside a small, pear - shaped peduncle — a false fruit.","Network_cn":"每颗腰果位于一条梨形的小肉茎中, 也就是假果.","tts_mp3":"http://res-tts.iciba.com/tts_new_dj//c/c/6/cc62287e1aa5a21bab124f72ad8094fd.mp3","tts_size":"23K","source_type":0,"source_id":0,"source_title":"普通双语例句"}],"netmean":{"PerfectNetExp":[{"id":"287632","key":"peduncle","exp":"花序梗","url":"http://www.enread.com/job/words/31926.html","bas":432,"abs":"生物学专业英语词汇(P)_专业词汇_英文阅读网 ... pedosphere 土壤圈 peduncle 花序梗 pedunculate bodies 蕈形体."},{"id":"659696","key":"peduncle","exp":"茎","url":"http://www.soenglish.com.cn/vocation/medical/200701/20070119201525_47759.html","bas":141,"abs":"医学制药词汇P ... pedophobia 儿童恐怖 peduncle 茎 pedunculated polyp 有脚性息肉."},{"id":"687856","key":"peduncle","exp":"花梗","url":"http://zhidao.baidu.com/question/137128653.html","bas":133,"abs":"用英文写出花的各组成部分_百度知道 ... 花被 perianth 花梗 peduncle 花瓣 petal."},{"id":"1057689","key":"peduncle","exp":"脚","url":"http://www.iciba.com/%E8%8A%B1%E6%A2%97","bas":77,"abs":"1. peduncularpeduncle 脚pedunculate 有梗的"}],"RelatedPhrase":[{"word":"cerebral peduncle","list":[{"id":"428920","key":"cerebral peduncle","exp":"大脑脚","url":"http://www.dxy.cn/bbs/post/view?bid=11&id=726905&sty","bas":252,"abs":"cerebral paragonimiasis 脑型肺吸虫病cerebral peduncle 大脑脚cerebral plasy 脑性瘫痪"}]},{"word":"mammillary peduncle","list":[{"id":"3517926","key":"mammillary peduncle","exp":"乳头脚","url":"http://www.dxy.cn/bbs/post/view?bid=11&id=726905&sty","bas":13,"abs":"mammillary body 乳头体mammillary peduncle 乳头脚mammillary region 乳头区"}]},{"word":"caudal peduncle","list":[{"id":"2570343","key":"caudal peduncle","exp":"尾柄","url":"http://tieba.baidu.com/p/768665699","bas":23,"abs":"（转帖）有关鼠鱼。_热带鱼吧_百度贴吧 ... 23)臀鳍 anal fin 24)尾柄 caudal peduncle 17]胸鳍椎刺 pectoral fin spine."}]},{"word":"floccular peduncle","list":[{"id":"1986112","key":"floccular peduncle","exp":"绒球脚","url":"http://www.dxy.cn/bbs/post/view?bid=11&id=726905&sty","bas":35,"abs":"flickering vision 闪烁视觉floccular peduncle 绒球脚flocculonodular syndrome 小脑绒球结节综合征."}]}]},"derivation":[{"yuyuan_name":"mid 18th cent.: from modern Latin pedunculus, from Latin pes, ped- 'foot'"}],"ee_mean":[{"part_name":"Noun","means":[{"word_mean":"1. the thin process of tissue that attaches a polyp to the body","sentences":[]},{"word_mean":"2. stalk bearing an inflorescence or solitary flower","sentences":[]},{"word_mean":"3. a bundle of myelinated neurons joining different parts of the brain","sentences":[]}]}],"traditional":"","_word_flag":1,"exchanges":["peduncle"]}