{"errno":0,"errmsg":"success","baesInfo":{"word_name":"lawfulness","is_CRI":"0","exchange":{"word_pl":[],"word_third":[],"word_past":[],"word_done":[],"word_ing":[],"word_er":[],"word_est":[],"word_prep":[],"word_adv":["lawfully"],"word_verb":[],"word_noun":[],"word_adj":["lawful"],"word_conn":[]},"symbols":[{"ph_en":"'lɔ:flnəs","ph_am":"'lɔflnəs","ph_other":"","ph_en_mp3":"","ph_am_mp3":"","ph_tts_mp3":"http://res-tts.iciba.com/c/5/e/c5e31021e3d5966ed26726dbd43dbb55.mp3","parts":[{"part":"","means":["法制，合法"]}]}],"translate_type":1},"sentence":[{"Network_id":"462209","Network_en":"Einstein declared that randomness rather than lawfulness is the characteristic of natural events.","Network_cn":"爱因斯坦宣称自然现象的特征为不可测性而不是规律化.","tts_mp3":"http://res-tts.iciba.com/tts_new_dj//e/d/b/edbfe92fbc5f6723f04766fe78425005.mp3","tts_size":"26K","source_type":0,"source_id":0,"source_title":"普通双语例句"},{"Network_id":"686550","Network_en":"Does the Lawfulness of War Matter?","Network_cn":"战争的合法性有关系 吗 ?","tts_mp3":"http://res-tts.iciba.com/tts_new_dj//2/a/7/2a7c648d75247b0a38d8d05b278106fa.mp3","tts_size":"10K","source_type":0,"source_id":0,"source_title":"普通双语例句"},{"Network_id":"726866","Network_en":"Article 7 In fixing prices, business operators should follow the principle of fairness , lawfulness , honesty and trustworthiness.","Network_cn":"第七条经营者定价, 应当遵循公平 、 法和诚实信用的原则.","tts_mp3":"http://res-tts.iciba.com/tts_new_dj//b/4/f/b4f4e531b642e80e6f16f0eeae936115.mp3","tts_size":"44K","source_type":0,"source_id":0,"source_title":"普通双语例句"}],"netmean":{"PerfectNetExp":[{"id":"271346","key":"lawfulness","exp":"合法性","url":"http://www.dsc.com.tw/dscbook/BOOK/38/38-1.htm","bas":468,"abs":"合法性(Lawfulness) 事先性(Prearrangement) 选择性(Selectivity)  机率性(Probability) 多样性(Diversity)  及时性(Timeliness)"},{"id":"534640","key":"lawfulness","exp":"法制","url":"http://iask.sina.com.cn/b/311997.html","bas":186,"abs":"... 4. rationality n. 合理性, 唯理性 5. lawfulness n. 法制,合法 6. quantification n. 资格, 条件, 限制, 限定, 赋予资格."},{"id":"3738739","key":"lawfulness","exp":"法律性","url":"http://book.zi5.me/books/read/2126/24","bas":11,"abs":"极权主义的法律性（lawfulness）是假装发现了一条在地球上建立公正统治的道路——这是成文法承认永远不可能达到的法律性。法律 …"}],"RelatedPhrase":[{"word":"proper law","list":[{"id":"20920","key":"proper law","exp":"自体法","url":"http://www.edu24ol.com/web_news/html/2010-10/201010200134165956.html","bas":10404,"abs":"　　D.尽管“自体法”(proper law)的概念最早是在合同领域提出的，但现在包括侵权行为在内，都有各自的“自体法”　　21.关于侵权行为的法 …"}]},{"word":"civil law","list":[{"id":"15996","key":"civil law","exp":"民法","url":"http://www.fanyijia.com/news_view.asp?id=864","bas":14004,"abs":"法律词汇_翻译家(Fanyijia.com) ... 面值 nominal value 民法 civil law 民法典 Civil Code."}]},{"word":"international law","list":[{"id":"9680","key":"international law","exp":"国际法","url":"http://baike.baidu.com/search/word?word=%E5%9B%BD%E9%99%85%E6%B3%95","bas":24888,"abs":"加利福尼亚大学伯克利分校_百度百科 ... Environmental Law 环境法 International Law 国际法（international law） Law Firms Rank Schools 律师学."}]},{"word":"criminal law","list":[{"id":"9533","key":"criminal law","exp":"刑法","url":"http://zhidao.baidu.com/question/91830269.html","bas":25368,"abs":"刑怎么组词_百度知道 ... [punishment and execution] 刑罚或处死 [criminal law] 刑法 [torture room] 用刑的房间(多指非法的)."}]}]},"ee_mean":[{"part_name":"Noun","means":[{"word_mean":"1. the quality of conforming to law","sentences":[]}]}],"traditional":"","_word_flag":1,"exchanges":["lawfully","lawful","lawfulness"]}