{"errno":0,"errmsg":"success","baesInfo":{"word_name":"foolishly","is_CRI":"1","exchange":{"word_pl":[],"word_third":[],"word_past":[],"word_done":[],"word_ing":[],"word_er":[],"word_est":[],"word_prep":[],"word_adv":[],"word_verb":[],"word_noun":["foolishness"],"word_adj":["foolish"],"word_conn":[]},"symbols":[{"ph_en":"'fu:lɪʃlɪ","ph_am":"ˈfulɪʃlɪ","ph_other":"","ph_en_mp3":"","ph_am_mp3":"http://res.iciba.com/resource/amp3/1/0/e5/18/e51865747518846de6a37a6f4dacfe86.mp3","ph_tts_mp3":"http://res-tts.iciba.com/e/5/1/e51865747518846de6a37a6f4dacfe86.mp3","parts":[{"part":"adv.","means":["愚蠢地，可笑地"]}]}],"frequence":2,"translate_type":1},"sentence":[{"Network_id":"2336368","Network_en":"He saw me standing there, grinning foolishly at him.","Network_cn":"他看见我站在那里，傻乎乎地咧着嘴朝他笑。","tts_mp3":"http://res-tts.iciba.com/tts_new_dj//b/5/a/b5a417c4d9ffc589ddebfd3eb6e0a3a2.mp3","tts_size":"15K","source_type":0,"source_id":0,"source_title":"普通双语例句"},{"Network_id":"2361087","Network_en":"He admitted that he had acted foolishly.","Network_cn":"他承认自己的行为很愚蠢。","tts_mp3":"http://res-tts.iciba.com/tts_new_dj//3/2/d/32de04f944e512416f885d978d540275.mp3","tts_size":"12K","source_type":0,"source_id":0,"source_title":"普通双语例句"},{"Network_id":"692233","Network_en":"Some boys are always playing the giddy goat, behaving foolishly.","Network_cn":"有些男孩子常常胡闹, 举止荒唐.","tts_mp3":"http://res-tts.iciba.com/tts_new_dj//4/b/8/4b879488f358ef89cbaeae601547829d.mp3","tts_size":"19K","source_type":0,"source_id":0,"source_title":"普通双语例句"}],"netmean":{"PerfectNetExp":[{"id":"732992","key":"foolishly","exp":"愚蠢地","url":"http://word.langfly.com/a/20120313/192840.shtml","bas":123,"abs":"高中英语单词表 ... football n. 足球；足球赛；美式足球 foolishly adv. 愚蠢地；荒谬地 foolish a. 愚蠢的，荒谬的，可笑的."},{"id":"969405","key":"foolishly","exp":"愚笨地","url":"http://www.guandang.com/txt/560336.html","bas":86,"abs":"F layer 电离层_馆档网 ... foolish 愚蠢的 foolishly 愚笨地 foolocracy 愚人统治."},{"id":"2100306","key":"foolishly","exp":"愚蠢地，荒唐可笑地","url":"http://www.iciba.com/ridiculously/","bas":32,"abs":"ridiculously是什么意思... ... absurdly ad. ridiculously1.  可笑地，荒谬地 ad. foolishly;ridiculously1. 愚蠢地，荒唐可笑地."},{"id":"3351359","key":"foolishly","exp":"荒谬地","url":"http://blog.163.com/star9917/blog/static/81967340201093041148761/","bas":14,"abs":"act vi. 行动；做，做事foolishly adv. 愚蠢地；荒谬地paw n. 脚爪"}],"RelatedPhrase":[{"word":"scholar foolishly","list":[{"id":"5477978","key":"scholar foolishly","exp":"学者愚蠢","url":"http://dj.iciba.com","bas":5,"abs":"the scholar foolishly had the educate cooling pool for swimming pool .学者愚蠢的把学院的冷却池当成游泳池。"}]},{"word":"speaks foolishly","list":[{"id":"4930107","key":"speaks foolishly","exp":"说傻话","url":"http://dj.iciba.com","bas":6,"abs":"People make fun of her because she always speaks foolishly ., 人们嘲笑她 , 因为她常说傻话."}]},{"word":"I foolishly","list":[{"id":"5976214","key":"I foolishly","exp":"我愚蠢地","url":"http://dj.iciba.com","bas":4,"abs":"but I foolishly let him a secret that I soon intended to a newspaper , and might then have work for him .但是我愚蠢地告诉他我有意办报的密秘，说那时也许就有工作了。"}]},{"word":"behaving foolishly","list":[{"id":"8197377","key":"behaving foolishly","exp":"做法很愚蠢","url":"http://dj.iciba.com","bas":3,"abs":"i venture that you are behaving foolishly ., 我冒昧说一句 , 你的做法很愚蠢."}]}]},"collins":[{"entry":[{"posp":"ADJ-GRADED","tran":"(举止或行为)愚蠢的，傻的，笨的","def":"If someone's behaviour or action is foolish, it is not sensible and shows a lack of good judgment.","example":[{"ex":"It would be foolish to raise hopes unnecessarily...","tran":"无谓地燃起人们的希望是愚蠢的。","tts_mp3":"http://res-tts.iciba.com/tts_dj/4/2/3/42386aea1b13f220d77c00ecbfc7c3a6.mp3","tts_size":"14K"},{"ex":"It is foolish to risk skin cancer.","tran":"冒患上皮肤癌的风险是愚蠢的。","tts_mp3":"http://res-tts.iciba.com/tts_dj/f/e/a/feafd28babdf1be81263aff5ed0e5a31.mp3","tts_size":"11K"}]},{"posp":"ADJ-GRADED","tran":"傻的;蠢的;显得难堪的","def":"If you look or feel foolish, you look or feel so silly or ridiculous that people are likely to laugh at you.","example":[{"ex":"I just stood there feeling foolish and watching him...","tran":"我只是傻傻地站在那里看着他。","tts_mp3":"http://res-tts.iciba.com/tts_dj/a/5/7/a5733a2f4e217d9a897efbf720ce64d8.mp3","tts_size":"14K"},{"ex":"I didn't want him to look foolish and be laughed at.","tran":"我不希望见到他出丑，被别人嘲笑。","tts_mp3":"http://res-tts.iciba.com/tts_dj/7/c/a/7ca0938a1870dc7af5c062a1efc7e0cf.mp3","tts_size":"14K"}]}]}],"ee_mean":[{"part_name":"Adverb","means":[{"word_mean":"1. without good sense or judgment;","sentences":[{"sentence":"\"He acted foolishly when he agreed to come\""}]}]}],"auth_sentence":[{"id":"403370","content":"Real mathematicians do not foolishly ignore such things.","link":"http://www.scientificamerican.com/article.cfm?id=six-things-ben-stein-doesnt-want-you-to-know&print=true","short_link":"http://www.scientificamerican.com/raekh","source":"SA","score":"0.975","cache_status":"1","tts_mp3":"http://res-tts.iciba.com/tts_authority/7/5/5/75501a3792c043b507823015a8d22b4f.mp3","tts_size":"18.0","diff":"3","oral":"0","res_content":"Real mathematicians do not <b>foolishly</b> ignore such things.","res_content_con":"Real mathematicians do not foolishly ignore such things.","res_key":"75501a3792c043b507823015a8d22b4f","source_type":0,"source_id":0,"source_title":"普通权威例句"},{"id":"1018057","content":"He should have come to her, she thought foolishly.","link":"http://www.newyorker.com/fiction/features/2010/11/29/101129fi_fiction_hunt?currentPage=all","short_link":"http://www.newyorker.com/69e5w","source":"NEWYORKER","score":"0.975","cache_status":"1","tts_mp3":"http://res-tts.iciba.com/tts_authority/c/9/3/c93b02010379d2d2ed9b0a374db43e55.mp3","tts_size":"14.0","diff":"3","oral":"0","res_content":"He should have come to her, she thought <b>foolishly</b>.","res_content_con":"He should have come to her, she thought foolishly.","res_key":"c93b02010379d2d2ed9b0a374db43e55","source_type":0,"source_id":0,"source_title":"普通权威例句"},{"id":"890146","content":"They foolishly believed there would be no more boom and bust.","link":"http://www.thetimes.co.uk/tto/opinion/columnists/article3311266.ece","short_link":"http://www.thetimes.co.uk/22aq5","source":"THETIMES","score":"0.9","cache_status":"1","tts_mp3":"http://res-tts.iciba.com/tts_authority/0/9/5/09542150e3c8d7282a3fb6d12d461a24.mp3","tts_size":"16.0","diff":"3","oral":"0","res_content":"They <b>foolishly</b> believed there would be no more boom and bust.","res_content_con":"They foolishly believed there would be no more boom and bust.","res_key":"09542150e3c8d7282a3fb6d12d461a24","source_type":0,"source_id":0,"source_title":"普通权威例句"}],"bidec":{"word_name":"foolishly","parts":[{"part_name":"adv.","word_id":"4477","part_id":"6011","means":[{"word_mean":"愚蠢地;可笑地","part_id":"6011","mean_id":"9969","sentences":[{"en":"She behaved foolishly but with good intent.","cn":"她表现得很愚蠢,不过用心却是好的。"},{"en":"I know I behaved foolishly but you needn’t rub it in.","cn":"我知道我的行为很愚蠢,但你不必老提那件事。"},{"en":"After a few drinks,the man felt no pain and began to act foolishly.","cn":"喝了一些酒之后,那人便醉了,开始做傻事。"}]}]}]},"traditional":"","_word_flag":1,"exchanges":["foolishness","foolish","foolishly"]}