{"errno":0,"errmsg":"success","netmean":{"PerfectNetExp":[],"RelatedPhrase":[{"word":"burts bees","list":[{"id":"50279","key":"burts bees","exp":"小蜜蜂","url":"http://www.beauty-life.com.cn/","bas":3929,"abs":"美丽约定时尚购物网-时尚自己就是这么简单 ... Broghese 贝佳斯 Burts bees 小蜜蜂 Benefit 美国贝玲妃."},{"id":"97434","key":"burts bees","exp":"蜜蜂爷爷","url":"http://bulls86015.blogspot.com/2010/09/ipod-touch-64g.html","bas":1773,"abs":"好康网购网: 博客来网路书局-iPod touch 64G ... Muses 保养品 BURTS BEES 蜜蜂爷爷 BURTS BEES 天然户外防护."}]},{"word":"burt's bee","list":[{"id":"3753296","key":"burt's bee","exp":"紫草膏","url":"http://www.bbkz.com/forum/showthread.php?t=1657&amp;page=4","bas":11,"abs":"紫草膏(burt's bee)防蚊液(burt's bee &amp; 香茅油)护唇膏(burt's bee)乾洗手药品视个人需求决定，根据我在那边生病的经验和大家分享一."}]}]},"traditional":"","baesInfo":{"translate_result":"hurtful有害的，伤感情的","translate_type":2,"translate_lang":"en-EU","ciba_translate_result":"","ciba_translate_msg":"以上结果来自机器翻译。","praise_open_close":1,"translate_msg":"以上结果来自机器翻译。","word_name":"burtful"},"word_name":"burtful","result_from":"fanyi","_word_flag":1,"exchanges":["burtful"]}