{"errno":0,"errmsg":"success","ee_mean":[{"part_name":"Noun","means":[{"word_mean":"1. a member of a sect;","sentences":[{"sentence":"\"most sectarians are intolerant of the views of any other sect\""}]}]}],"traditional":"","baesInfo":{"translate_result":"secularist现世主义者，世俗主义者","translate_type":2,"translate_lang":"en-EU","ciba_translate_result":"","ciba_translate_msg":"以上结果来自机器翻译。","praise_open_close":1,"translate_msg":"以上结果来自机器翻译。","word_name":"sectarist"},"word_name":"sectarist","result_from":"fanyi","_word_flag":1,"exchanges":["sectarist"]}