{"errno":0,"errmsg":"success","baesInfo":{"word_name":"splendid","is_CRI":"1","exchange":{"word_pl":[],"word_third":[],"word_past":[],"word_done":[],"word_ing":[],"word_er":[],"word_est":[],"word_prep":[],"word_adv":["splendidly"],"word_verb":[],"word_noun":[],"word_adj":[],"word_conn":[]},"symbols":[{"ph_en":"ˈsplendɪd","ph_am":"ˈsplɛndɪd","ph_other":"","ph_en_mp3":"http://res.iciba.com/resource/amp3/oxford/0/91/8f/918f438ce5fc304bb6f93a97e0848fc8.mp3","ph_am_mp3":"http://res.iciba.com/resource/amp3/1/0/29/1e/291e4e17891fea6049b26893fa00af57.mp3","ph_tts_mp3":"http://res-tts.iciba.com/2/9/1/291e4e17891fea6049b26893fa00af57.mp3","parts":[{"part":"adj.","means":["壮观的，豪华的","极好的或令人满意的","闪亮的","为众人所推崇的"]}]}],"frequence":2,"word_tag":[0,1,2,5],"translate_type":1},"sameAnalysis":[{"part_name":"这些形容词均有\"极好的\"之意。","word_list":"excellent, choice, splendid, select, prime, first-rate","means":["excellent ： 通常指事物在等级品位以及职位级别等方面的最优或接近最优。","choice ： 指通过精心挑选达到水平，尤指罕见或品质精良的商品。","splendid ： 口语常用词，指非常令人满意，显得完美无缺。","select ： 指精挑细选出来作为范例的物或人。","prime ： 常指最重要、价值最高的东西，也可以表示最佳、最典型或最高的人或物。","first-rate ： 多用于指对抽象事物的主观评估，有时含夸大、自负的意味。"]},{"part_name":"这些形容词都含有\"宏伟壮丽的\"之意。","word_list":"grand, magnificent, majestic, splendid, noble","means":["grand ： 侧重规模大，豪华而宏伟壮丽、盛大。也可指人的崇高、伟大。","magnificent ： 指环境、建筑物等本身的壮丽、堂皇、庄严、崇高或出色等。","majestic ： 侧重状态、外表、仪态等给人以威严感。","splendid ： 指人在行为、品德或性格等方面的卓越超群；指物侧重外观上的辉煌。用于口语中，作\"极好的，绝妙的\"解。","noble ： 指因本身著名或从外表上看有令人难忘的华丽、庄严、卓越、雄壮或崇高。"]},{"part_name":"这些形容词均含\"华丽的，宏传的，辉煌的\"之意。","word_list":"splendid, gorgeous, glorious, superb, magnificent","means":["splendid ： 侧重指给观察者留下壮丽辉煌或灿烂夺目的印象。","gorgeous ： 指色彩的富丽和豪华，有时含炫耀和卖弄意味。","glorious ： 指光芒四射的绚丽，也指值得称倾、赞美或扬名的壮丽辉煌。 ","superb ： 指壮丽辉煌、宏伟等的极点。","magnificent ： 侧重指建筑物、宝石等的华丽堂皇。"]}],"sentence":[{"Network_id":"2316862","Network_en":"The house commanded some splendid views of Delaware Bay.","Network_cn":"从这座房子可以俯瞰到特拉华湾壮丽的景致。","tts_mp3":"http://res-tts.iciba.com/tts_new_dj//d/a/5/da56a64f1873bf8edc54340b5cf16739.mp3","tts_size":"16K","source_type":0,"source_id":0,"source_title":"普通双语例句"},{"Network_id":"2344726","Network_en":"Our house has got a splendid view across to the Cotswolds.","Network_cn":"从我们的房子里向外望去，景色宜人，一直能看到科茨沃尔德丘陵。","tts_mp3":"http://res-tts.iciba.com/tts_new_dj//b/2/d/b2d7118cc397307eda8c8aec6a0e43a1.mp3","tts_size":"18K","source_type":0,"source_id":0,"source_title":"普通双语例句"},{"Network_id":"2347179","Network_en":"She was attended by servants in splendid livery and powdered wigs.","Network_cn":"她由穿着华丽制服、头戴扑粉假发的仆人们伺候着。","tts_mp3":"http://res-tts.iciba.com/tts_new_dj//0/9/3/09371e594d4106cbd65100ab82b031b0.mp3","tts_size":"19K","source_type":0,"source_id":0,"source_title":"普通双语例句"}],"netmean":{"PerfectNetExp":[{"id":"96646","key":"splendid","exp":"极好的","url":"http://www.douban.com/group/topic/5295583/","bas":1791,"abs":"高中英语新课程标准词汇表 ... spit v. 吐唾沫；吐痰 splendid a. 灿烂的，辉煌的；（口语）极好的 split v. 撕开； 切开."},{"id":"100883","key":"splendid","exp":"壮丽的","url":"http://wenku.baidu.com/view/d8fd61f0f61fb7360b4c653a.html","bas":1698,"abs":"高二英语必修五单词列表_百度文库 ... uniform n. 制服 splendid adj. 壮丽的 statue n. 雕像."},{"id":"109381","key":"splendid","exp":"辉煌的","url":"http://pp949330.blog.163.com/blog/static/533456312007102443054141/","bas":1536,"abs":"洛奇魔法释放卷轴接头 - 　　　叶的日志 - 网易博客 ... 奇特的 Singular 辉煌的 Splendid 精密的 Strict."},{"id":"241939","key":"splendid","exp":"辉煌","url":"http://tieba.baidu.com/p/265466259","bas":544,"abs":"魔法释放卷_洛奇吧_百度贴吧 ... 奇特的 Singular 辉煌 Splendid 精密 Strict."}],"RelatedPhrase":[{"word":"splendid isolation","list":[{"id":"570519","key":"splendid isolation","exp":"光荣孤立","url":"http://zh.wikipedia.org/wiki/%E5%85%89%E6%A6%AE%E5%AD%A4%E7%AB%8B","bas":170,"abs":"光荣孤立（Splendid isolation） 是19世纪晚期英国追求的外交政策，由本杰明&#183;迪斯雷利与罗伯特&#183;盖斯科因-塞西尔（索尔兹伯里侯爵…"},{"id":"735381","key":"splendid isolation","exp":"光辉孤立","url":"http://baike.baidu.com/search/word?word=%E5%85%89%E8%BE%89%E5%AD%A4%E7%AB%8B","bas":122,"abs":"“光辉孤立（splendid isolation）”（Splendid Isolation）：19世纪60年代到20世纪初,英国政府...开放分类： 历史 &#183;外交中日联合声明中华人民共和国政府和 …"}]},{"word":"splendid china","list":[{"id":"694144","key":"splendid china","exp":"锦绣中华","url":"http://zhidao.baidu.com/question/97547069.html","bas":132,"abs":"深圳景点用英语怎么读？_百度知道 ... 世界之窗 Window of the world 锦绣中华 Splendid China 红树林 Red Wood."}]},{"word":"splendid holiday","list":[{"id":"1214445","key":"splendid holiday","exp":"人人假期","url":"http://www.usalifeonline.com/f/list.php?fid=338&amp;city_id=3&amp;page=4","bas":65,"abs":"美国西部旅行社 ... 惠亚旅游 Sophia's Tours‎ 人人假期 Splendid Holiday‎ 华安旅行社 Stanley's Travel‎."}]},{"word":"splendid attire","list":[{"id":"384063","key":"splendid attire","exp":"盛装","url":"http://wenwen.soso.com/z/q179496276.htm","bas":292,"abs":"盛的多音字组词 - 已解决 - 搜搜问问 ... 36. 盛馔[ rich diet] 37. 盛装[ splendid attire] 38. 盛壮[ strong]."}]}]},"phrase":[{"cizu_name":"splendid isolation","jx":[{"jx_en_mean":"used to emphasize the isolation of a person or thing","jx_cn_mean":"［用于突出人或物所处的孤立状态］光荣的孤立；庄严的孤立","lj":[{"lj_ly":"the stone stands &B{in splendid isolation} near the moorland road.","lj_ls":"这块石头孑然傲立于沼地公路的近旁。"}]}]}],"synonym":[{"part_name":"adj.","means":[{"word_mean":"灿烂的;壮丽的;辉煌的","cis":["grand","magnificent","brilliant","resplendent","glorious","wonderful","fine","superb","gorgeous","excellent"]}]},{"part_name":"","means":[{"word_mean":"其他释义","cis":["marvelous","glorious","excellent","signal","fine","good","vivid","dashing","imposing","regal","brilliant","grand","golden","sumptuous","illustrious","costly","flashy","stately","magnificent","wealthy"]}]}],"antonym":[{"part_name":"adj.","means":[{"word_mean":"灿烂的;杰出的","cis":["obscure","plain","dull","ordinary"]}]},{"part_name":"","means":[{"word_mean":"其他释义","cis":["ordinary"]}]}],"derivation":[{"yuyuan_name":"early 17th cent.: from French splendide or Latin splendidus, from splendere 'shine, be bright'"}],"collins":[{"entry":[{"posp":"ADJ-GRADED","tran":"极好的;绝妙的;出色的","def":"If you say that something is splendid, you mean that it is very good.","example":[{"ex":"The book includes a wealth of splendid photographs...","tran":"该书中有大量精彩的照片。","tts_mp3":"http://res-tts.iciba.com/tts_dj/4/4/4/4442d1cb9cc0bba31b4c088f7e1fe223.mp3","tts_size":"15K"},{"ex":"Our house has got a splendid view across to the Cotswolds...","tran":"从我们的房子里向外望去，景色宜人，一直能看到科茨沃尔德丘陵。","tts_mp3":"http://res-tts.iciba.com/tts_dj/c/6/8/c68a94824fe21e6ef2c0eacbe96cac6e.mp3","tts_size":"18K"}]},{"posp":"ADJ-GRADED","tran":"(建筑、艺术作品)壮丽的，华丽的，美妙的","def":"If you describe a building or work of art as splendid, you mean that it is beautiful, impressive, and extremely well made.","example":[{"ex":"...a splendid Victorian mansion.","tran":"华丽的维多利亚式宅第","tts_mp3":"http://res-tts.iciba.com/tts_dj/0/c/2/0c29711756df483b930f0afbfb396cff.mp3","tts_size":"10K"}]},{"posp":"EXCLAM","tran":"好极了(表示赞同)","def":"You can say 'splendid' in a conversation to indicate that you approve of a particular situation or something that someone has said.","example":[{"ex":"'I was thinking I might do a lemon cream sauce and baked potatoes.' 'Splendid!' Midge applauded.","tran":"“我在考虑做一道浇柠檬奶油汁的烤马铃薯。”“好极了！”米基表示赞同。","tts_mp3":"http://res-tts.iciba.com/tts_dj/3/d/5/3d5409feda32aea2c9b20c97695eacb3.mp3","tts_size":"35K"}]}]}],"ee_mean":[{"part_name":"Adjective","means":[{"word_mean":"1. having great beauty and splendor;","sentences":[{"sentence":"\"a glorious spring morning\""},{"sentence":"\"a glorious sunset\""},{"sentence":"\"splendid costumes\""},{"sentence":"\"a kind of splendiferous native simplicity\""}]},{"word_mean":"2. characterized by or attended with brilliance or grandeur;","sentences":[{"sentence":"\"the brilliant court life at Versailles\""},{"sentence":"\"a glorious work of art\""},{"sentence":"\"magnificent cathedrals\""},{"sentence":"\"the splendid coronation ceremony\""}]}]}],"auth_sentence":[{"id":"151210","content":"They looked splendid and the sun flashed on their...accoutrements.","link":"None","short_link":"None","source":"J. Rathbone","score":"1","cache_status":"1","tts_mp3":"http://res-tts.iciba.com/tts_authority/c/4/c/c4c6a42675693ebde635cab5dad9b7d2.mp3","tts_size":"21.0","diff":"3","oral":"0","res_content":"They looked <b>splendid</b> and the sun flashed on their...accoutrements.","res_content_con":"They looked splendid and the sun flashed on their...accoutrements.","res_key":"c4c6a42675693ebde635cab5dad9b7d2","source_type":0,"source_id":0,"source_title":"普通权威例句"},{"id":"153282","content":"We were assigned splendid apartments in the new palace.","link":"None","short_link":"None","source":"G. Vidal","score":"1","cache_status":"1","tts_mp3":"http://res-tts.iciba.com/tts_authority/b/b/0/bb0b91a17879199ae31bcb6dfbab5647.mp3","tts_size":"14.0","diff":"2","oral":"0","res_content":"We were assigned <b>splendid</b> apartments in the new palace.","res_content_con":"We were assigned splendid apartments in the new palace.","res_key":"bb0b91a17879199ae31bcb6dfbab5647","source_type":0,"source_id":0,"source_title":"普通权威例句"},{"id":"129898","content":"A splendid speaker, with a strong, well-modulated voice.","link":"None","short_link":"None","source":"S. Rosenberg","score":"0.975","cache_status":"1","tts_mp3":"http://res-tts.iciba.com/tts_authority/7/1/1/7113458af64da8f856101a9ca7fecaca.mp3","tts_size":"20.0","diff":"2","oral":"0","res_content":"A <b>splendid</b> speaker, with a strong, well-modulated voice.","res_content_con":"A splendid speaker, with a strong, well-modulated voice.","res_key":"7113458af64da8f856101a9ca7fecaca","source_type":0,"source_id":0,"source_title":"普通权威例句"}],"stems_affixes":[{"type":"词根","type_value":"splend","type_exp":"=shine,表示\"发光\"","word_parts":[{"word_part":"adj.","stems_affixes":[{"value_en":"resplendent","value_cn":"辉煌的","word_buile":"re再+splend光辉+ent……的→再光辉→辉煌的"},{"value_en":"splendid","value_cn":"壮丽的,辉煌的;极好的","word_buile":"splend发光+id……的→adj.壮丽的,辉煌的;极好的"}]},{"word_part":"n.","stems_affixes":[{"value_en":"splendor","value_cn":"壮丽,辉煌","word_buile":"splend发光+or表名词→n.壮丽,辉煌"}]}]}],"bidec":{"word_name":"splendid","parts":[{"part_name":"adj.","word_id":"26466","part_id":"34900","means":[{"word_mean":"极好的","part_id":"34900","mean_id":"68038","sentences":[{"en":"He got a splendid present for her.","cn":"他送她一件极好的礼物。"},{"en":"His reputation as a statesman is splendid.","cn":"作为政治家, 他的名声极好。"},{"en":"It was splendid of you to make the offer.","cn":"你提的这个建议太好了。"},{"en":"It's splendid that you are here.","cn":"你在这儿太好了。"}]},{"word_mean":"壮丽的;  辉煌的","part_id":"34900","mean_id":"68039","sentences":[{"en":"The splendid hall dazzled the young man.","cn":"富丽堂皇的大厅使那年轻人眼花缭乱。"}]}]}]},"jushi":[{"english":"It's a splendid example of stupidity.","chinese":"这是愚蠢的最佳例子。","mp3":"http://res-tts.iciba.com/tts_synusage/6/2/3/623f6e7e33cb1b5a568ffc23ac2c20b8.mp3"},{"english":"That's a splendid idea.","chinese":"那是个极好的主意。","mp3":"http://res-tts.iciba.com/tts_synusage/a/0/e/a0e7c5e9021d9a9b315e74f5ea19cd6d.mp3"},{"english":"They told the Emperor that he should get new clothes made of this splendid cloth for the coming great procession.","chinese":"他们对皇帝说他应该用块绚丽多彩的布料做一身新衣服,好参加即将举行的盛大游行。","mp3":"http://res-tts.iciba.com/tts_synusage/1/3/9/1397eb020a62b9749946bc9eb266b449.mp3"}],"traditional":"","_word_flag":1,"exchanges":["splendidly","splendid"]}