{"errno":0,"errmsg":"success","baesInfo":{"word_name":"stabilization","is_CRI":"1","exchange":{"word_pl":[],"word_third":[],"word_past":[],"word_done":[],"word_ing":[],"word_er":[],"word_est":[],"word_prep":[],"word_adv":[],"word_verb":["stabilize"],"word_noun":[],"word_adj":[],"word_conn":[]},"symbols":[{"ph_en":"ˌsteɪbəlaɪ'zeɪʃn","ph_am":"ˌsteɪbəlaɪ'zeɪʃn","ph_other":"","ph_en_mp3":"http://res.iciba.com/resource/amp3/0/0/21/59/21591e8572ae3be539fab61aeb6d7014.mp3","ph_am_mp3":"http://res.iciba.com/resource/amp3/1/0/21/59/21591e8572ae3be539fab61aeb6d7014.mp3","ph_tts_mp3":"http://res-tts.iciba.com/2/1/5/21591e8572ae3be539fab61aeb6d7014.mp3","parts":[{"part":"n.","means":["稳定性","稳定化","安定面"]}]}],"frequence":2,"translate_type":1},"trade_means":[{"word_trade":"体育","word_mean":["坚定法","安定","稳定"]},{"word_trade":"医学","word_mean":["安定：稳定状态的形成"]},{"word_trade":"土木工程","word_mean":["稳定"]},{"word_trade":"数学","word_mean":["镇定"]},{"word_trade":"物理学","word_mean":["稳定化"]},{"word_trade":"电子学","word_mean":["稳定"]},{"word_trade":"电工","word_mean":["稳定"]},{"word_trade":"自动化","word_mean":["镇定"]}],"netmean":{"PerfectNetExp":[{"id":"57804","key":"stabilization","exp":"稳定","url":"http://www.douban.com/group/topic/4824898/","bas":3358,"abs":"英语词根词缀记忆大全 ... spirit 精神） &quot;267. stabilization n 稳定，安定（来自 stabilize 稳定）."},{"id":"163519","key":"stabilization","exp":"稳定化","url":"http://wiki.mbalib.com/wiki/%E9%A1%B9%E7%9B%AE%E7%AE%A1%E7%90%86%E6%9C%AF%E8%AF%AD%E8%8B%B1%E6%B1%89%E5%AF%B9%E7%85%A7%E8%A1%A8","bas":913,"abs":"项目管理术语英汉对照表 - MBA智库百科 ... Stability 稳定性 Stabilization 稳定化 Staff 人员."},{"id":"295962","key":"stabilization","exp":"镇定","url":"http://www.yizhil.com/show-6-84-1.html","bas":416,"abs":"stability limit 稳定极限stabilization 镇定，稳定Stackelberg decision theory 施塔克尔贝格决策理论."},{"id":"591384","key":"stabilization","exp":"稳定作用","url":"http://www.docin.com/p-161583584.html","bas":162,"abs":"KedarHastak报道EGCG诱导人前列腺癌(carcinomaofDros诅te)LNCaP细胞的凋亡是通过调节两个相关的途径:(a)采用关键的丝氨酸残基磷酸化来对p53的稳定作用(stabilization)."}],"RelatedPhrase":[{"word":"stability","list":[{"id":"18475","key":"stability","exp":"稳定性","url":"http://www.iosh.gov.tw/Book/Report_Publish.aspx?PID=1508&amp;UID=F6619","bas":11950,"abs":"稳定性，我们会先执行稳定性(stability)评估。"},{"id":"137649","key":"stability","exp":"安定","url":"http://www.fanyijia.com/news_view.asp?id=1407","bas":1144,"abs":"普通英汉小词典_翻译家(Fanyijia.com) ... stab 刺 stability 安定 stable 坚固的."}]},{"word":"stabilizer","list":[{"id":"64245","key":"stabilizer","exp":"稳定器","url":"http://baike.baidu.com/search/word?word=%E7%A8%B3%E5%AE%9A%E5%99%A8","bas":2964,"abs":"电气工程专业英语_百度百科 ... stabilization network 稳定网络 stabilizer 稳定器 air-gap flux 气隙磁通."},{"id":"68166","key":"stabilizer","exp":"稳定剂","url":"http://dyangxj1981.blog.163.com/blog/static/111488095200931611503215/","bas":2746,"abs":"岩土力学与工程 5 - 大观园的日志 - 网易博客 ... stabilization 加固，固化 stabilizer 加固剂；稳定剂 stack structure 堆垛结构."}]}]},"collins":[{"entry":[{"posp":"V-ERG","tran":"(使)稳定;(使)安定","def":"If something stabilizes, or is stabilized, it becomes stable.","example":[{"ex":"Although her illness is serious, her condition is beginning to stabilize...","tran":"虽然她病得很重，但病情正开始趋于稳定。","tts_mp3":"http://res-tts.iciba.com/tts_dj/b/0/b/b0bfb7f797ccd48458d7d14f7c3e71af.mp3","tts_size":"22K"},{"ex":"Officials hope the move will stabilize exchange rates...","tran":"官员们希望此举能使汇率稳定下来。","tts_mp3":"http://res-tts.iciba.com/tts_dj/6/2/7/6273916288633acae8112402c561b19c.mp3","tts_size":"16K"}]}]}],"ee_mean":[{"part_name":"Noun","means":[{"word_mean":"1. the act of stabilizing something or making it more stable;","sentences":[{"sentence":"\"he worked for price stabilization for farm products\""},{"sentence":"\"wage stabilization is necessary for industrial peace\""},{"sentence":"\"stabilization means that the product can be handled under atmospheric conditions\""}]},{"word_mean":"2. the act of making something (as a vessel or aircraft) less likely to overturn","sentences":[]}]}],"auth_sentence":[{"id":"1219353","content":"And there were a little bit of signs of stabilization in the housing market.","link":"http://www.msnbc.msn.com/id/43918150/ns/msnbc_tv-hardball_with_chris_matthews/","short_link":"http://www.msnbc.msn.com/8yaqj","source":"MSN","score":"0.375","cache_status":"1","tts_mp3":"http://res-tts.iciba.com/tts_authority/4/e/d/4ed4d3a9ed08822f6478285f644a992c.mp3","tts_size":"20.0","diff":"2","oral":"0","res_content":"And there were a little bit of signs of <b>stabilization</b> in the housing market.","res_content_con":"And there were a little bit of signs of stabilization in the housing market.","res_key":"4ed4d3a9ed08822f6478285f644a992c","source_type":0,"source_id":0,"source_title":"普通权威例句"},{"id":"1145332","content":"\"It's associated with the steering and stabilization of the rocket during flight, \" Diller said of the faulty hardware.","link":"http://www.msnbc.msn.com/id/33351268/","short_link":"http://www.msnbc.msn.com/cfdbc","source":"MSN","score":"0.08","cache_status":"1","tts_mp3":"http://res-tts.iciba.com/tts_authority/8/3/4/834126a5a2f65ab48777008af5c8b1e7.mp3","tts_size":"32.0","diff":"3","oral":"0","res_content":"\"It's associated with the steering and <b>stabilization</b> of the rocket during flight, \" Diller said of the faulty hardware.","res_content_con":"\"It's associated with the steering and stabilization of the rocket during flight, \" Diller said of the faulty hardware.","res_key":"834126a5a2f65ab48777008af5c8b1e7","source_type":0,"source_id":0,"source_title":"普通权威例句"},{"id":"1154454","content":"President Bush signed the bill, called the Emergency Economic Stabilization Act, on Oct. 3.","link":"http://topics.nytimes.com/top/reference/timestopics/people/p/henry_m_jr_paulson/index.html","short_link":"http://topics.nytimes.com/yzuj4","source":"NYTIMES","score":"0.08","cache_status":"1","tts_mp3":"http://res-tts.iciba.com/tts_authority/e/b/e/ebe45499240570c9c20bb4f5fdbb4d54.mp3","tts_size":"30.0","diff":"2","oral":"0","res_content":"President Bush signed the bill, called the Emergency Economic <b>Stabilization</b> Act, on Oct. 3.","res_content_con":"President Bush signed the bill, called the Emergency Economic Stabilization Act, on Oct. 3.","res_key":"ebe45499240570c9c20bb4f5fdbb4d54","source_type":0,"source_id":0,"source_title":"普通权威例句"}],"stems_affixes":[{"type":"词根","type_value":"sta","type_exp":"=stand,表示\"站,立\"","word_parts":[{"word_part":"n.","stems_affixes":[{"value_en":"stability","value_cn":"稳定,安定","word_buile":"stab=stable稳定的,安定的+ility→n.稳定,安定"},{"value_en":"stabilization","value_cn":"稳定性","word_buile":"stabil=stable稳定的,安定的+ization表名词→来自stability"},{"value_en":"stage","value_cn":"舞台，戏剧；阶段，时期","word_buile":"sta站,立+age场所,状态等→n.舞台，戏剧；阶段，时期"},{"value_en":"stay","value_cn":"逗留, 延缓, 中止, 支柱 ","word_buile":"sta站,立+y→n.逗留, 延缓, 中止, 支柱 v.在, 暂住"}]},{"word_part":"v.","stems_affixes":[{"value_en":"establish","value_cn":"建立,设立,安置,确定 ","word_buile":"e=ex+stable牢固的+ish表动词→establish使其完全牢固→建立,设立,安置"},{"value_en":"stay","value_cn":"在, 暂住","word_buile":"sta站,立+y→n.逗留, 延缓, 中止, 支柱 v.在, 暂住"}]}]}],"traditional":"","_word_flag":1,"exchanges":["stabilize","stabilization"]}