{"errno":0,"errmsg":"success","baesInfo":{"word_name":"nonporous","is_CRI":"1","exchange":{"word_pl":[],"word_third":[],"word_past":[],"word_done":[],"word_ing":[],"word_er":[],"word_est":[],"word_prep":[],"word_adv":[],"word_verb":[],"word_noun":[],"word_adj":[],"word_conn":[]},"symbols":[{"ph_en":"'nɒn'pɔ:rəs","ph_am":"'nɒn'pɔrəs","ph_other":"","ph_en_mp3":"http://res.iciba.com/resource/amp3/0/0/8c/ea/8cea180f6965b085a11359f0ee887fea.mp3","ph_am_mp3":"http://res.iciba.com/resource/amp3/1/0/8c/ea/8cea180f6965b085a11359f0ee887fea.mp3","ph_tts_mp3":"http://res-tts.iciba.com/8/c/e/8cea180f6965b085a11359f0ee887fea.mp3","parts":[{"part":"n.","means":["无孔的"]}]}],"word_tag":[3],"translate_type":1},"sentence":[{"Network_id":"2238914","Network_en":"These nonporous surfaces paint badly with a brush.","Network_cn":"这些无孔的表面很难以刷子上漆。","tts_mp3":"http://res-tts.iciba.com/tts_new_dj//2/f/1/2f1c6f64ca393d3839026e99edbe77ad.mp3","tts_size":"15K","source_type":0,"source_id":0,"source_title":"普通双语例句"},{"Network_id":"1086625","Network_en":"Fine point dry ease markers for white board and other nonporous surface.","Network_cn":"圆头笔尖,书写笔型白板笔,可在各种白板和光滑表面书写.","tts_mp3":"http://res-tts.iciba.com/tts_new_dj//1/a/d/1adf770e825d9703587aee9ca4b8379c.mp3","tts_size":"21K","source_type":0,"source_id":0,"source_title":"普通双语例句"},{"Network_id":"1599449","Network_en":"All interior walls, floors and ceiling are constructed with hard, nonporous, non - shedding materials.","Network_cn":"所有内部墙壁 、 地板和天花板均采用硬质 、 无孔 、 不脱落材料建造.","tts_mp3":"http://res-tts.iciba.com/tts_new_dj//9/7/0/970e1d6fe49780fb286800b4ccd8540f.mp3","tts_size":"35K","source_type":0,"source_id":0,"source_title":"普通双语例句"}],"netmean":{"PerfectNetExp":[{"id":"391088","key":"nonporous","exp":"无孔的","url":"http://www.zhuoda.org/xiexindeboke/108409.html","bas":285,"abs":"GRE词汇精选（核心词汇） ... nonflammable 不易燃的 nonporous 无孔的，不渗透的 nonradioactive 非放射性的."},{"id":"850161","key":"nonporous","exp":"无孔隙的","url":"http://www.the1.com.cn/infosort_the1/info/23905-1.htm","bas":101,"abs":"石油词汇英语翻译(NO) -亿城英语 ... nonporosity 无孔性 nonporous 无孔隙的 nonpreemptive service 无优先服务."},{"id":"1159154","key":"nonporous","exp":"不渗透的","url":"http://www.docin.com/p-2342865.html","bas":69,"abs":"关于陶瓷的英语专业术语 - 豆丁网 ... 半透明 translucence,translucency,translucent 不渗透的 nonporous 不透明的 opaque."}],"RelatedPhrase":[{"word":"nonporous membrane","list":[{"id":"11593931","key":"nonporous membrane","exp":"非多孔膜","url":"http://baike.baidu.com/view/1955043.htm","bas":2,"abs":"...收藏查看致密膜又称非多孔膜(nonporous membrane)主要由物质的晶区和组成的在0.5～1nm小于10%为0.1～1.25μm具有透过性的或聚合物膜dense membrane."},{"id":"14855869","key":"nonporous membrane","exp":"又称非多孔膜","url":"http://baike.baidu.com/view/1955043.htm","bas":1,"abs":"dense membrane又称非多孔膜(nonporous membrane) 。主要由物质的晶区和无定形区组成的。孔径在0.5～1nm，孔隙率小于10％，厚度为0.1～1.25μm具有透过性的无机物或聚合物膜。"}]},{"word":"nonporous wood","list":[{"id":"2627546","key":"nonporous wood","exp":"无孔材","url":"http://www.wood168.com/data/hp/GB%EF%BC%8DT%2014019-1992%20%20%E6%9C%A8%E6%9D%90%E9%98%B2%E8%85%90%E6%9C%AF%E8%AF%AD.asp","bas":22,"abs":"...木材产自针叶树，属裸子植物。在大多数情况下，具有针形或鳞片状的树叶。同义词　软材或无孔材（nonporous wood）2.40　阔叶树材　broadleaves wood，hard wood."}]}]},"ee_mean":[{"part_name":"Adjective","means":[{"word_mean":"1. not porous; especially not having vessels that appear as pores;","sentences":[{"sentence":"\"nonporous wood\""}]}]}],"traditional":"","_word_flag":1,"exchanges":["nonporous"]}