{"errno":0,"errmsg":"success","baesInfo":{"word_name":"recurve","is_CRI":"0","exchange":{"word_pl":[],"word_third":["recurves"],"word_past":["recurved"],"word_done":["recurved"],"word_ing":["recurving"],"word_er":[],"word_est":[],"word_prep":[],"word_adv":[],"word_verb":[],"word_noun":[],"word_adj":[],"word_conn":[]},"symbols":[{"ph_en":"rɪ'kɜ:v","ph_am":"rɪ'kɜv","ph_other":"","ph_en_mp3":"http://res.iciba.com/resource/amp3/0/0/b4/a5/b4a51126fac7607ce52be15b778ba928.mp3","ph_am_mp3":"","ph_tts_mp3":"http://res-tts.iciba.com/b/4/a/b4a51126fac7607ce52be15b778ba928.mp3","parts":[{"part":"v.","means":["（使）向后弯曲"]}]}],"translate_type":1},"trade_means":[{"word_trade":"体育","word_mean":["弓片端头弯部"]}],"sentence":[{"Network_id":"260934","Network_en":"DOLPHIN is expected to recurve after it traverses the ridge axis.","Network_cn":"白海豚将沿副热带高压脊西转西北面向北转东北移动.","tts_mp3":"http://res-tts.iciba.com/tts_new_dj//c/e/a/cea6c48a682b138ec16815d290984f26.mp3","tts_size":"20K","source_type":0,"source_id":0,"source_title":"普通双语例句"},{"Network_id":"873104","Network_en":"NAKRI will pass through the weakness between the high pressure and recurve.","Network_cn":"娜基莉将通过围绕它的两个高压中之弱点向北后转东北移动.","tts_mp3":"http://res-tts.iciba.com/tts_new_dj//8/2/b/82b1152d6fc6409b136b3068516ff1ae.mp3","tts_size":"22K","source_type":0,"source_id":0,"source_title":"普通双语例句"},{"Network_id":"1004101","Network_en":"NAKRI will traverse the ridge axis of the steering subtropical ridge and recurve.","Network_cn":"娜基莉将横过副热带高压脊的脊线向北后转东北移动.","tts_mp3":"http://res-tts.iciba.com/tts_new_dj//b/a/d/bad277fd99a08b887ed1e88a763cdffb.mp3","tts_size":"25K","source_type":0,"source_id":0,"source_title":"普通双语例句"}],"netmean":{"PerfectNetExp":[{"id":"900520","key":"recurve","exp":"向后弯曲","url":"http://www.cihui.biz/html/94/n-11194.html","bas":94,"abs":"recurvature 折回原来方向recurve 向后弯曲recurved 内弯的"},{"id":"2814414","key":"recurve","exp":"反曲弓","url":"http://www.epochtimes.com/gb/8/1/23/n1987551.htm","bas":19,"abs":"射箭可分反曲弓（recurve）、复合（compound）弓二种，亚运及奥运只有反曲弓，世界赛、亚洲赛则包含复合弓。但是，二者比赛 …"},{"id":"2981435","key":"recurve","exp":"下弯或后弯的","url":"http://www.scientrans.com/vocabulary/pages2/238_82_11.html","bas":17,"abs":"生物学名词词汇R-11|植物学英语词汇翻译... ... 下弯 recurvation 下弯或后弯的 recurved 红藻 red algae;Rhodophyta."},{"id":"4843827","key":"recurve","exp":"弓的尾端向上弯的部分","url":"http://www.360doc.com/content/06/0323/18/5368_84876.shtml","bas":7,"abs":"上弯部[弓的尾端向上弯的部分](recurve) 箭(arrow) 矢舎[接弦的部分](nock) 矢羽[前末端的羽毛](fletching) [箭柄基部](shaftment/."}],"RelatedPhrase":[{"word":"recurved occlusion","list":[{"id":"3119859","key":"recurved occlusion","exp":"后曲锢囚锋","url":"http://www.enfans.com/16/061B93462008.shtml","bas":16,"abs":"recurvature 转向recurved occlusion 后曲锢囚锋recurved spit 钩状岬"},{"id":"8272968","key":"recurved occlusion","exp":"后曲囚锢","url":"http://photino.cwb.gov.tw/rdcweb/lib/h/h_000744.htm","bas":2,"abs":"recurved occlusion 后曲囚锢 2 M  recycled water 再循环水 M  red rain 红雨  red tide 红潮  red-noise type 红噪型 M  redctive 约化扰动 M  red."}]},{"word":"recurve bow","list":[{"id":"4109019","key":"recurve bow","exp":"反曲之弓","url":"http://lol.sgamer.com/news/200911/37143_3.html","bas":9,"abs":"LoL初级攻略阿什-寒冰射手_lol英雄联盟... ... +手斧( pickaxe) +反曲之弓( recurve bow) +匕首( dagger)."},{"id":"5831658","key":"recurve bow","exp":"曲弓","url":"http://dj.iciba.com","bas":5,"abs":"Australian Matt Gray aim at a yellow circle from 70m away no bigger than a thumbprint-and released an arrow from his recurve bow .澳大利亚的马特·格雷瞄准一个黄圆圈（即黄心)——在70米开外看上去只有个拇指印儿那么大——然后用他那反曲弓把箭射了出去。"}]},{"word":"recurved spit","list":[{"id":"1072672","key":"recurved spit","exp":"弯曲沙嘴","url":"http://bbs.urelitetech.com.cn/forum.php?mod=viewthread&tid=652","bas":76,"abs":"recurrence interval (reture period) 重现期recurved spit 弯曲沙嘴recycling 再循环"},{"id":"2103552","key":"recurved spit","exp":"钩状岬","url":"http://www.enfans.com/16/061B93462008.shtml","bas":32,"abs":"recurved occlusion 后曲锢囚锋recurved spit 钩状岬recycle engine 闭路循环发动机"}]},{"word":"rarely recurved","list":[{"id":"11797650","key":"rarely recurved","exp":"很少下弯","url":"http://dj.iciba.com","bas":1,"abs":"awn 12 –16 mm , geniculate or rarely recurved ;, 芒 12-16 毫米 , 膝曲的或很少下弯;"}]}]},"derivation":[{"yuyuan_name":"late 16th cent.: from Latin recurvare 'bend (something) back', from re- 'back' + curvare 'to bend'"}],"ee_mean":[{"part_name":"Verb","means":[{"word_mean":"1. curve or bend (something) back or down","sentences":[]}]}],"auth_sentence":[{"id":"280999","content":"Hunt has switched from compound to recurve in pursuit of an Olympic place.","link":"http://www.bbc.co.uk/sport/0/archery/14016824","short_link":"http://www.bbc.co.uk/yn748","source":"BBC","score":"0.6","cache_status":"1","tts_mp3":"http://res-tts.iciba.com/tts_authority/3/0/f/30f2ee2ab49c7dc68b666d5691a38560.mp3","tts_size":"21.0","diff":"3","oral":"0","res_content":"Hunt has switched from compound to <b>recurve</b> in pursuit of an Olympic place.","res_content_con":"Hunt has switched from compound to recurve in pursuit of an Olympic place.","res_key":"30f2ee2ab49c7dc68b666d5691a38560","source_type":0,"source_id":0,"source_title":"普通权威例句"},{"id":"280451","content":"The compound bow is more technically advanced and more accurate than the recurve so scores are usually higher.","link":"http://www.bbc.co.uk/sport2/hi/archery/7580819.stm","short_link":"http://www.bbc.co.uk/zcjz6","source":"BBC","score":"0.08","cache_status":"1","tts_mp3":"http://res-tts.iciba.com/tts_authority/c/6/3/c639973c91b555718b5ee9554dea5075.mp3","tts_size":"30.0","diff":"3","oral":"0","res_content":"The compound bow is more technically advanced and more accurate than the <b>recurve</b> so scores are usually higher.","res_content_con":"The compound bow is more technically advanced and more accurate than the recurve so scores are usually higher.","res_key":"c639973c91b555718b5ee9554dea5075","source_type":0,"source_id":0,"source_title":"普通权威例句"},{"id":"280456","content":"Both the recurve bow and compound bow feature at Commonwealth Games but only the recurve bow is used at the Olympics.","link":"http://www.bbc.co.uk/sport2/hi/archery/7580819.stm","short_link":"http://www.bbc.co.uk/ynawg","source":"BBC","score":"0.08","cache_status":"1","tts_mp3":"http://res-tts.iciba.com/tts_authority/4/4/c/44cd588267b63f6d160d0c43a109088d.mp3","tts_size":"32.0","diff":"3","oral":"0","res_content":"Both the <b>recurve</b> bow and compound bow feature at Commonwealth Games but only the <b>recurve</b> bow is used at the Olympics.","res_content_con":"Both the recurve bow and compound bow feature at Commonwealth Games but only the recurve bow is used at the Olympics.","res_key":"44cd588267b63f6d160d0c43a109088d","source_type":0,"source_id":0,"source_title":"普通权威例句"}],"traditional":"","_word_flag":1,"exchanges":["recurves","recurved","recurved","recurving","recurve"]}