{"errno":0,"errmsg":"success","baesInfo":{"word_name":"admirer","is_CRI":"1","exchange":{"word_pl":["admirers"],"word_third":[],"word_past":[],"word_done":[],"word_ing":[],"word_er":[],"word_est":[],"word_prep":[],"word_adv":[],"word_verb":[],"word_noun":[],"word_adj":[],"word_conn":[]},"symbols":[{"ph_en":"ədˈmaɪərə(r)","ph_am":"ədˈmaɪərər","ph_other":"","ph_en_mp3":"http://res.iciba.com/resource/amp3/oxford/0/c3/e1/c3e1420cd41441e75887f6d8082c7ee1.mp3","ph_am_mp3":"http://res.iciba.com/resource/amp3/1/0/17/38/17381a989ad09c0997d5e7117488f9a9.mp3","ph_tts_mp3":"http://res-tts.iciba.com/1/7/3/17381a989ad09c0997d5e7117488f9a9.mp3","parts":[{"part":"n.","means":["赞赏者","羡慕者","崇拜者","（女子的）爱慕者"]}]}],"frequence":1,"translate_type":1},"sentence":[{"Network_id":"2328099","Network_en":"I think Tessa should plump for Malcolm, her long-suffering admirer.","Network_cn":"我想特莎应该选择长期默默爱慕她的马尔科姆。","tts_mp3":"http://res-tts.iciba.com/tts_new_dj//f/5/a/f5a28cc9cd791859ade0e1d4c4c9b74c.mp3","tts_size":"21K","source_type":0,"source_id":0,"source_title":"普通双语例句"},{"Network_id":"2346502","Network_en":"He was an admirer of her grandfather's paintings.","Network_cn":"他非常欣赏她祖父的画作。","tts_mp3":"http://res-tts.iciba.com/tts_new_dj//3/4/a/34a1fc8e522cfc61edf07d647dccff67.mp3","tts_size":"14K","source_type":0,"source_id":0,"source_title":"普通双语例句"},{"Network_id":"2251577","Network_en":"He is a great admirer of Picasso's early paintings.","Network_cn":"他十分赞赏毕加索的早期画作。","tts_mp3":"http://res-tts.iciba.com/tts_new_dj//6/1/a/61aab7ae87be9ba9fcf98c5dcaa70615.mp3","tts_size":"17K","source_type":0,"source_id":0,"source_title":"普通双语例句"}],"netmean":{"PerfectNetExp":[{"id":"17810","key":"admirer","exp":"爱慕者","url":"http://blog.sina.com.cn/u/1665413904","bas":12465,"abs":"EchoLin_新浪博客 ... 顶尖选手： all-star 爱慕者： admirer 你已有什么心事： whenever sth is bothering you."},{"id":"406224","key":"admirer","exp":"仰慕者","url":"http://wenku.baidu.com/view/629cb41f650e52ea551898d8.html","bas":271,"abs":"英语专业八级词汇表_百度文库 ... adjustment n. 调节 admirer n. 钦佩者,仰慕者,求爱者 ado n. 忙乱，骚扰."},{"id":"883909","key":"admirer","exp":"钦佩者","url":"http://wenku.baidu.com/view/629cb41f650e52ea551898d8.html","bas":96,"abs":"英语专业八级词汇表_百度文库 ... adjustment n. 调节 admirer n. 钦佩者,仰慕者,求爱者 ado n. 忙乱，骚扰."},{"id":"1552672","key":"admirer","exp":"景慕者","url":"http://www.ntweida.cn/English/2008523/El147.html","bas":49,"abs":"admire 赞美admirer 景慕者admiring 赞赏的"}],"RelatedPhrase":[{"word":"admirable","list":[{"id":"203349","key":"admirable","exp":"可贵","url":"http://bbs.topys.cn/thread-1092-1-1.html","bas":684,"abs":"大连华通和平海岸样本部分文案 - 创意侃吧 -... ... Earth 超值 Admirable 可贵 Convenient 便利."}]},{"word":"admire","list":[{"id":"21230","key":"admire","exp":"钦佩","url":"http://wenku.baidu.com/view/dbdfbf62783e0912a2162af9.html","bas":10220,"abs":"2012英语四级词汇复习资料_百度文库 ... administration n. 管理； admire vt. 钦佩，羡慕，赞赏 admission n. 允许进入；承认."},{"id":"24379","key":"admire","exp":"羡慕","url":"http://www.zdic.net/zd/zi/ZdicE5Zdic96Zdic84.htm","bas":8744,"abs":"字典中善字的解释 ... (3) 通“缮”。修治[ repair] (5) 羡慕[ admire] (6) 喜爱[ like]."}]}]},"collins":[{"entry":[{"posp":"N-COUNT","tran":"钦佩者；欣赏者","def":"If you are an admirer of someone, you like and respect them or their work very much.","example":[{"ex":"He was an admirer of her grandfather's paintings.","tran":"他非常欣赏她祖父的画作。","tts_mp3":"http://res-tts.iciba.com/tts_dj/3/4/a/34a1fc8e522cfc61edf07d647dccff67.mp3","tts_size":"14K"}]},{"posp":"N-COUNT","tran":"（女人的）追求者,爱慕者","def":"A woman's admirers are the men who are attracted to her.","example":[{"ex":"Johnny was the most persistent and most harmless of her admirers.","tran":"约翰尼是追她的人中最痴心、最没有心机的一个。","tts_mp3":"http://res-tts.iciba.com/tts_dj/8/5/4/85452965673f39c249ba18a793f0fb82.mp3","tts_size":"20K"}]}]}],"ee_mean":[{"part_name":"Noun","means":[{"word_mean":"1. a person who backs a politician or a team etc.;","sentences":[{"sentence":"\"all their supporters came out for the game\""},{"sentence":"\"they are friends of the library\""}]},{"word_mean":"2. a person who admires; someone who esteems or respects or approves","sentences":[]},{"word_mean":"3. someone who admires a young woman;","sentences":[{"sentence":"\"she had many admirers\""}]}]}],"auth_sentence":[{"id":"99584","content":"I was always an admirer of Dada and Surrealism.","link":"http://www.thetimes.co.uk/tto/arts/visualarts/photography/article2577420.ece","short_link":"http://www.thetimes.co.uk/z4xfn","source":"THETIMES","score":"1","cache_status":"1","tts_mp3":"http://res-tts.iciba.com/tts_authority/7/0/6/706b7f338208656d3bf17185da164485.mp3","tts_size":"15.0","diff":"3","oral":"0","res_content":"I was always an <b>admirer</b> of Dada and Surrealism.","res_content_con":"I was always an admirer of Dada and Surrealism.","res_key":"706b7f338208656d3bf17185da164485","source_type":0,"source_id":0,"source_title":"普通权威例句"},{"id":"101373","content":"But King was a great admirer of the Israeli state.","link":"http://www.thetimes.co.uk/tto/news/world/middleeast/article3720532.ece","short_link":"http://www.thetimes.co.uk/b7qhc","source":"THETIMES","score":"0.975","cache_status":"1","tts_mp3":"http://res-tts.iciba.com/tts_authority/3/3/b/33b4c45240922bdbb46d32426e041b8b.mp3","tts_size":"15.0","diff":"1","oral":"0","res_content":"But King was a great <b>admirer</b> of the Israeli state.","res_content_con":"But King was a great admirer of the Israeli state.","res_key":"33b4c45240922bdbb46d32426e041b8b","source_type":0,"source_id":0,"source_title":"普通权威例句"},{"id":"755614","content":"Today she wears a handmade bracelet sent by an admirer.","link":"http://www.voanews.com/content/palestinian-american-poet-bridges-2-cultures-121082294/162479.html","short_link":"http://www.voanews.com/mnfab","source":"VOA","score":"0.975","cache_status":"1","tts_mp3":"http://res-tts.iciba.com/tts_authority/7/6/e/76e568dc01aa7ed1a18eca9cf280600f.mp3","tts_size":"15.0","diff":"3","oral":"0","res_content":"Today she wears a handmade bracelet sent by an <b>admirer</b>.","res_content_con":"Today she wears a handmade bracelet sent by an admirer.","res_key":"76e568dc01aa7ed1a18eca9cf280600f","source_type":0,"source_id":0,"source_title":"普通权威例句"}],"bidec":{"word_name":"admirer","parts":[{"part_name":"n.","word_id":"537","part_id":"847","means":[{"word_mean":"赞赏者;羡慕者；崇拜者","part_id":"847","mean_id":"1504","sentences":[{"en":"There was a little cluster of admirers round the guest speaker.","cn":"有一小群仰慕者围着那位特邀嘉宾。"}]},{"word_mean":"(女子的)爱慕者，追求者","part_id":"847","mean_id":"1505","sentences":[{"en":"Of all her admirers the most permanent was Sir John.","cn":"在她所有的爱慕者当中，约翰爵士最有恒心。"},{"en":"Her admirers were fewer, and fatter, and less ardent.","cn":"她的爱慕者少一些, 胖一些, 感情不那么热烈。"}]}]}]},"traditional":"","_word_flag":1,"exchanges":["admirers","admirer"]}